<?xml version="1.0" encoding="utf-8"?>
<level>
	<!-- Nodes -->
	<node type="group">
		<type>Conveyor_Normal</type>
		<position>9,2</position>
		<tail>9,8</tail>
		<facing>DOWN</facing>
		<clickable>true</clickable>
	</node>
	<node type="group">
		<type>Conveyor_Normal</type>
		<position>3,2</position>
		<tail>8,2</tail>
		<facing>LEFT</facing>
		<clickable>true</clickable>
	</node>
	<node type="group">
		<type>Conveyor_Normal</type>
		<position>2,5</position>
		<tail>8,5</tail>
		<facing>RIGHT</facing>
		<clickable>true</clickable>
	</node>
	<node type="group">
		<type>Conveyor_Normal</type>
		<position>10,8</position>
		<tail>14,8</tail>
		<facing>RIGHT</facing>
		<clickable>true</clickable>
	</node>
	
	<!-- Bins -->
	<node type="single">
		<type>Bin_Normal</type>
		<position>9,1</position>
		<color>0x0000ff</color>
	</node>
	<node type="single">
		<type>Bin_Normal</type>
		<position>9,9</position>
		<color>0xffff00</color>
	</node>
	<node type="single">
		<type>Bin_Normal</type>
		<position>1,5</position>
	</node>
	
	<!-- Mail -->
	<mail>
		<type>Mail_Normal</type>
		<position>7,2</position>
		<color>0xffff00</color>
	</mail>
	<mail>
		<type>Mail_Normal</type>
		<position>3,5</position>
	</mail>
	<mail>
		<type>Mail_Normal</type>
		<position>10,8</position>
		<color>0x0000ff</color>
	</mail>
	
	<!-- Time -->
	<time>
		<value>0:30</value>
	</time>
</level>