{  
   "nodes":[  
      {  
         "clickable":true,
         "x":7,
         "y":4,
         "type":"NodeHolder",
         "capacity":3
      },
      {  
         "subtype":"NodeConveyorNormal",
         "clickable":true,
         "y1":0,
         "x1":7,
         "y2":3,
         "x2":7,
         "dir":"down",
         "type":"NodeGroupRect"
      },
      {  
         "subtype":"NodeConveyorNormal",
         "clickable":true,
         "y1":4,
         "x1":2,
         "y2":4,
         "x2":6,
         "dir":"right",
         "type":"NodeGroupRect"
      },
      {  
         "subtype":"NodeConveyorNormal",
         "clickable":true,
         "y1":4,
         "x1":8,
         "y2":4,
         "x2":12,
         "dir":"left",
         "type":"NodeGroupRect"
      },
      {  
         "subtype":"NodeConveyorNormal",
         "clickable":true,
         "y1":5,
         "x1":7,
         "y2":7,
         "x2":7,
         "dir":"down",
         "type":"NodeGroupRect"
      },
      {  
         "clickable":true,
         "x":7,
         "y":8,
         "dir":"down",
         "type":"NodeConveyorRotate"
      },
      {  
         "color":15,
         "clickable":false,
         "x":7,
         "y":9,
         "type":"NodeBin"
      },
      {  
         "subtype":"NodeConveyorNormal",
         "clickable":true,
         "y1":8,
         "x1":8,
         "y2":8,
         "x2":9,
         "dir":"right",
         "type":"NodeGroupRect"
      },
      {  
         "subtype":"NodeConveyorNormal",
         "clickable":true,
         "y1":8,
         "x1":5,
         "y2":8,
         "x2":6,
         "dir":"left",
         "type":"NodeGroupRect"
      },
      {  
         "clickable":true,
         "x":4,
         "y":8,
         "dir":"down",
         "type":"NodeConveyorNormal"
      },
      {  
         "clickable":true,
         "x":10,
         "y":8,
         "dir":"down",
         "type":"NodeConveyorNormal"
      },
      {  
         "color":15,
         "clickable":false,
         "x":10,
         "y":9,
         "type":"NodeBin"
      },
      {  
         "color":15,
         "clickable":false,
         "x":4,
         "y":9,
         "type":"NodeBin"
      }
   ],
   "notes":[  

   ],
   "mail":[  
      {  
         "color":15,
         "x":7,
         "y":0,
         "type":"MailNormal"
      },
      {  
         "x":2,
         "y":4,
         "type":"MailMagnetic",
         "polarity":1
      },
      {  
         "x":12,
         "y":4,
         "type":"MailContraband"
      }
   ],
   "meta":{  
      "name-internal":"holder",
      "format":"PP-level",
      "format-version":1,
      "name-external":"Holder"
   }
}